invis.py
invis-1.0.1.dist-info/LICENSE
invis-1.0.1.dist-info/METADATA
invis-1.0.1.dist-info/WHEEL
invis-1.0.1.dist-info/top_level.txt
invis-1.0.1.dist-info/RECORD
