Metadata-Version: 2.1
Name: invis
Version: 1.0.1
Summary: An invisible framework for enforcing type checking at runtime.
Home-page: https://github.com/dxflores/invis
Author: Diogo Flores
Author-email: dxflores@outlook.com
License: UNKNOWN
Platform: UNKNOWN
Classifier: Development Status :: 3 - Alpha
Classifier: Intended Audience :: Developers
Classifier: License :: OSI Approved :: MIT License
Classifier: Programming Language :: Python :: 3.7
Requires-Python: >=3.7
Provides-Extra: test
Requires-Dist: pytest ; extra == 'test'
